lovis4u/DataProcessing.py
lovis4u/Drawing.py
lovis4u/Manager.py
lovis4u/Methods.py
lovis4u/__init__.py
lovis4u/lovis4u_data/.DS_Store
lovis4u/lovis4u_data/category_colors.tsv
lovis4u/lovis4u_data/help.txt
lovis4u/lovis4u_data/palette.txt
lovis4u/lovis4u_data/standard.cfg
lovis4u/lovis4u_data/bin/.DS_Store
lovis4u/lovis4u_data/bin/mmseqs_linux.zip
lovis4u/lovis4u_data/bin/mmseqs_mac/LICENSE.md
lovis4u/lovis4u_data/bin/mmseqs_mac/README.md
lovis4u/lovis4u_data/bin/mmseqs_mac/userguide.pdf
lovis4u/lovis4u_data/bin/mmseqs_mac/bin/mmseqs
lovis4u/lovis4u_data/bin/mmseqs_mac/examples/DB.fasta
lovis4u/lovis4u_data/bin/mmseqs_mac/examples/QUERY.fasta
lovis4u/lovis4u_data/bin/mmseqs_mac/matrices/PAM10.out
lovis4u/lovis4u_data/bin/mmseqs_mac/matrices/PAM100.out
lovis4u/lovis4u_data/bin/mmseqs_mac/matrices/PAM110.out
lovis4u/lovis4u_data/bin/mmseqs_mac/matrices/PAM120.out
lovis4u/lovis4u_data/bin/mmseqs_mac/matrices/PAM130.out
lovis4u/lovis4u_data/bin/mmseqs_mac/matrices/PAM140.out
lovis4u/lovis4u_data/bin/mmseqs_mac/matrices/PAM150.out
lovis4u/lovis4u_data/bin/mmseqs_mac/matrices/PAM160.out
lovis4u/lovis4u_data/bin/mmseqs_mac/matrices/PAM170.out
lovis4u/lovis4u_data/bin/mmseqs_mac/matrices/PAM180.out
lovis4u/lovis4u_data/bin/mmseqs_mac/matrices/PAM190.out
lovis4u/lovis4u_data/bin/mmseqs_mac/matrices/PAM20.out
lovis4u/lovis4u_data/bin/mmseqs_mac/matrices/PAM30.out
lovis4u/lovis4u_data/bin/mmseqs_mac/matrices/PAM40.out
lovis4u/lovis4u_data/bin/mmseqs_mac/matrices/PAM50.out
lovis4u/lovis4u_data/bin/mmseqs_mac/matrices/PAM60.out
lovis4u/lovis4u_data/bin/mmseqs_mac/matrices/PAM70.out
lovis4u/lovis4u_data/bin/mmseqs_mac/matrices/PAM80.out
lovis4u/lovis4u_data/bin/mmseqs_mac/matrices/PAM90.out
lovis4u/lovis4u_data/bin/mmseqs_mac/matrices/VTML10.out
lovis4u/lovis4u_data/bin/mmseqs_mac/matrices/VTML120.out
lovis4u/lovis4u_data/bin/mmseqs_mac/matrices/VTML160.out
lovis4u/lovis4u_data/bin/mmseqs_mac/matrices/VTML20.out
lovis4u/lovis4u_data/bin/mmseqs_mac/matrices/VTML40.out
lovis4u-0.0.3.1.dist-info/LICENSE
lovis4u-0.0.3.1.dist-info/LICENSE_dependencies
lovis4u-0.0.3.1.dist-info/METADATA
lovis4u-0.0.3.1.dist-info/WHEEL
lovis4u-0.0.3.1.dist-info/top_level.txt
lovis4u-0.0.3.1.dist-info/RECORD
