Metadata-Version: 2.1
Name: lovis4u
Version: 0.0.3.1
Summary: Loci Visualisation Tool.
Home-page: https://art-egorov.github.io/lovis4u/
Author: Artyom Egorov
Author-email: artem.egorov@med.lu.se
License: WTFPL
Requires-Python: >=3.8
License-File: LICENSE
License-File: LICENSE_dependencies
Requires-Dist: biopython
Requires-Dist: configs
Requires-Dist: argparse
Requires-Dist: distinctipy
Requires-Dist: pandas
Requires-Dist: reportlab
Requires-Dist: bcbio-gff
Requires-Dist: matplotlib
Requires-Dist: seaborn
Requires-Dist: scipy
